{"stem":"0005","instances":[{"docId":"A_0005","docUri":"A_0005.html","score":28,"contexts":[{"form":"0005","weight":"1","pos":74,"context":"...-images.acdh-dev.oeaw.ac.at\/ga\/A_<mark>0005<\/mark>_Seite_01","fid":"page"},{"form":"0005","weight":"1","pos":180,"context":"...-images.acdh-dev.oeaw.ac.at\/ga\/A_<mark>0005<\/mark>_Seite_02","fid":"page"},{"form":"0005","weight":"1","pos":280,"context":"...-images.acdh-dev.oeaw.ac.at\/ga\/A_<mark>0005<\/mark>_Seite_03","fid":"page"},{"form":"0005","weight":"1","pos":370,"context":"...-images.acdh-dev.oeaw.ac.at\/ga\/A_<mark>0005<\/mark>_Seite_04","fid":"page"},{"form":"0005","weight":"1","pos":465,"context":"...-images.acdh-dev.oeaw.ac.at\/ga\/A_<mark>0005<\/mark>_Seite_05","fid":"page"},{"form":"0005","weight":"1","pos":555,"context":"...-images.acdh-dev.oeaw.ac.at\/ga\/A_<mark>0005<\/mark>_Seite_06","fid":"page"},{"form":"0005","weight":"1","pos":646,"context":"...-images.acdh-dev.oeaw.ac.at\/ga\/A_<mark>0005<\/mark>_Seite_07","fid":"page"},{"form":"0005","weight":"1","pos":736,"context":"...-images.acdh-dev.oeaw.ac.at\/ga\/A_<mark>0005<\/mark>_Seite_08","fid":"page"},{"form":"0005","weight":"1","pos":832,"context":"...-images.acdh-dev.oeaw.ac.at\/ga\/A_<mark>0005<\/mark>_Seite_09","fid":"page"},{"form":"0005","weight":"1","pos":936,"context":"...-images.acdh-dev.oeaw.ac.at\/ga\/A_<mark>0005<\/mark>_Seite_10","fid":"page"},{"form":"0005","weight":"1","pos":1044,"context":"...-images.acdh-dev.oeaw.ac.at\/ga\/A_<mark>0005<\/mark>_Seite_11","fid":"page"},{"form":"0005","weight":"1","pos":1149,"context":"...-images.acdh-dev.oeaw.ac.at\/ga\/A_<mark>0005<\/mark>_Seite_12","fid":"page"},{"form":"0005","weight":"1","pos":1254,"context":"...-images.acdh-dev.oeaw.ac.at\/ga\/A_<mark>0005<\/mark>_Seite_13","fid":"page"},{"form":"0005","weight":"1","pos":1348,"context":"...-images.acdh-dev.oeaw.ac.at\/ga\/A_<mark>0005<\/mark>_Seite_14","fid":"page"},{"form":"0005","weight":"1","pos":1440,"context":"...-images.acdh-dev.oeaw.ac.at\/ga\/A_<mark>0005<\/mark>_Seite_15","fid":"page"},{"form":"0005","weight":"1","pos":1513,"context":"...-images.acdh-dev.oeaw.ac.at\/ga\/A_<mark>0005<\/mark>_Seite_16","fid":"page"},{"form":"0005","weight":"1","pos":1598,"context":"...-images.acdh-dev.oeaw.ac.at\/ga\/A_<mark>0005<\/mark>_Seite_17","fid":"page"},{"form":"0005","weight":"1","pos":1668,"context":"...-images.acdh-dev.oeaw.ac.at\/ga\/A_<mark>0005<\/mark>_Seite_18","fid":"page"},{"form":"0005","weight":"1","pos":1754,"context":"...-images.acdh-dev.oeaw.ac.at\/ga\/A_<mark>0005<\/mark>_Seite_19","fid":"page"},{"form":"0005","weight":"1","pos":1856,"context":"...-images.acdh-dev.oeaw.ac.at\/ga\/A_<mark>0005<\/mark>_Seite_20","fid":"page"},{"form":"0005","weight":"1","pos":1928,"context":"...-images.acdh-dev.oeaw.ac.at\/ga\/A_<mark>0005<\/mark>_Seite_21","fid":"page"},{"form":"0005","weight":"1","pos":2009,"context":"...-images.acdh-dev.oeaw.ac.at\/ga\/A_<mark>0005<\/mark>_Seite_22","fid":"page"},{"form":"0005","weight":"1","pos":2080,"context":"...-images.acdh-dev.oeaw.ac.at\/ga\/A_<mark>0005<\/mark>_Seite_23","fid":"page"},{"form":"0005","weight":"1","pos":2151,"context":"...-images.acdh-dev.oeaw.ac.at\/ga\/A_<mark>0005<\/mark>_Seite_24","fid":"page"},{"form":"0005","weight":"1","pos":2226,"context":"...-images.acdh-dev.oeaw.ac.at\/ga\/A_<mark>0005<\/mark>_Seite_25","fid":"page"},{"form":"0005","weight":"1","pos":2295,"context":"...-images.acdh-dev.oeaw.ac.at\/ga\/A_<mark>0005<\/mark>_Seite_26","fid":"page"},{"form":"0005","weight":"1","pos":2353,"context":"...-images.acdh-dev.oeaw.ac.at\/ga\/A_<mark>0005<\/mark>_Seite_27","fid":"page"},{"form":"0005","weight":"1","pos":2390,"context":"...-images.acdh-dev.oeaw.ac.at\/ga\/A_<mark>0005<\/mark>_Seite_28","fid":"page"}]},{"docId":"C_0005","docUri":"C_0005.html","score":12,"contexts":[{"form":"0005","weight":"1","pos":98,"context":"...-images.acdh-dev.oeaw.ac.at\/ph\/C_<mark>0005<\/mark>_Seite_01","fid":"page"},{"form":"0005","weight":"1","pos":200,"context":"...-images.acdh-dev.oeaw.ac.at\/ph\/C_<mark>0005<\/mark>_Seite_02","fid":"page"},{"form":"0005","weight":"1","pos":310,"context":"...-images.acdh-dev.oeaw.ac.at\/ph\/C_<mark>0005<\/mark>_Seite_03","fid":"page"},{"form":"0005","weight":"1","pos":409,"context":"...-images.acdh-dev.oeaw.ac.at\/ph\/C_<mark>0005<\/mark>_Seite_04","fid":"page"},{"form":"0005","weight":"1","pos":515,"context":"...-images.acdh-dev.oeaw.ac.at\/ph\/C_<mark>0005<\/mark>_Seite_05","fid":"page"},{"form":"0005","weight":"1","pos":604,"context":"...-images.acdh-dev.oeaw.ac.at\/ph\/C_<mark>0005<\/mark>_Seite_06","fid":"page"},{"form":"0005","weight":"1","pos":700,"context":"...-images.acdh-dev.oeaw.ac.at\/ph\/C_<mark>0005<\/mark>_Seite_07","fid":"page"},{"form":"0005","weight":"1","pos":805,"context":"...-images.acdh-dev.oeaw.ac.at\/ph\/C_<mark>0005<\/mark>_Seite_08","fid":"page"},{"form":"0005","weight":"1","pos":917,"context":"...-images.acdh-dev.oeaw.ac.at\/ph\/C_<mark>0005<\/mark>_Seite_09","fid":"page"},{"form":"0005","weight":"1","pos":1017,"context":"...-images.acdh-dev.oeaw.ac.at\/ph\/C_<mark>0005<\/mark>_Seite_10","fid":"page"},{"form":"0005","weight":"1","pos":1124,"context":"...-images.acdh-dev.oeaw.ac.at\/ph\/C_<mark>0005<\/mark>_Seite_11","fid":"page"},{"form":"0005","weight":"1","pos":1151,"context":"...-images.acdh-dev.oeaw.ac.at\/ph\/C_<mark>0005<\/mark>_Seite_12","fid":"page"}]}]}