{"stem":"0149","instances":[{"docId":"A_0149","docUri":"A_0149.html","score":5,"contexts":[{"form":"0149","weight":"1","pos":66,"context":"...-images.acdh-dev.oeaw.ac.at\/ga\/A_<mark>0149<\/mark>_Seite_01","fid":"page"},{"form":"0149","weight":"1","pos":128,"context":"...-images.acdh-dev.oeaw.ac.at\/ga\/A_<mark>0149<\/mark>_Seite_02","fid":"page"},{"form":"0149","weight":"1","pos":198,"context":"...-images.acdh-dev.oeaw.ac.at\/ga\/A_<mark>0149<\/mark>_Seite_03","fid":"page"},{"form":"0149","weight":"1","pos":266,"context":"...-images.acdh-dev.oeaw.ac.at\/ga\/A_<mark>0149<\/mark>_Seite_04","fid":"page"},{"form":"0149","weight":"1","pos":287,"context":"...-images.acdh-dev.oeaw.ac.at\/ga\/A_<mark>0149<\/mark>_Seite_05","fid":"page"}]}]}