{"stem":"abrégé","instances":[{"docId":"C_0001","docUri":"C_0001.html","score":2,"contexts":[{"form":"abrégée","weight":"1","pos":825,"context":"...les livres emportés en Chine etc. b Dissertation <mark>abrégée<\/mark> sur le nom antique et hiéroglyphique de la Judée...","fid":"p__36"},{"form":"abrégées","weight":"1","pos":832,"context":"...antique et hiéroglyphique de la Judée. c. Note <mark>abrégées<\/mark> relative aux Obosou Tumulus du Bosphore Cimmérien. d...","fid":"p__36"}]},{"docId":"C_0102","docUri":"C_0102.html","score":1,"contexts":[{"form":"\"Abrégé","weight":"1","pos":326,"context":"...Lloyd zu triest zum Geschenk eingesandt ein Exemplar seines: <mark>\"Abrégé<\/mark> de l'histoire des comtes de Gorice trieste 1851....","fid":"p__19"}]}]}