{"stem":"abändern","instances":[{"docId":"A_0096","docUri":"A_0096.html","score":1,"contexts":[{"form":"abändern","weight":"1","pos":117,"context":"...erbitten den § 48 der Geschäftsord- nung dahin <mark>abändern<\/mark> zu können, daß vom 1. Jän- ner 1856...","fid":"p__30"}]},{"docId":"C_0003","docUri":"C_0003.html","score":1,"contexts":[{"form":"abändern","weight":"1","pos":71,"context":"...den in ihrer vor- hergehenden Sitzung gefaßten Beschluß dahin <mark>abändern<\/mark>, daß sie diese Werke nicht als selbstständig herauszugebende...","fid":"p__38"}]}]}