{"stem":"an","instances":[{"docId":"C_0004","docUri":"C_0004.html","score":2,"contexts":[{"form":"ans","weight":"1","pos":897,"context":"..., daß dieses sehr bedeutende Werk sobald als möglich <mark>ans<\/mark> Tageslicht gezogen werde.\":\/","fid":"p__46"},{"form":"ans","weight":"1","pos":1300,"context":"...Bibliotheken und Archiven des In- und Auslandes liegenden Geschichtsquellen <mark>ans<\/mark> Licht zu ziehen, und ihren Werth zu würdigen...","fid":"p__19"}]},{"docId":"A_0132","docUri":"A_0132.html","score":1,"contexts":[{"form":"Ans","weight":"1","pos":295,"context":" ihr gerichtetes <mark>Ans<\/mark>- chen des Universitäts- Consistorium wegen Überlassung des...","fid":"p__9"}]},{"docId":"C_0025","docUri":"C_0025.html","score":1,"contexts":[{"form":"ans","weight":"1","pos":360,"context":"...beredt geschildert ist. Dem Papste wird in scharfen Worten <mark>ans<\/mark> Herz","fid":"p__14"}]}]}