{"stem":"anlaßt","instances":[{"docId":"A_0026","docUri":"A_0026.html","score":1,"contexts":[{"form":"anlaßt","weight":"1","pos":813,"context":"...Documente durch die A- quisition des Reichsarchivs ver- <mark>anlaßt<\/mark> worden, welches dem hie- sigen incorporirt werden soll....","fid":"p__33"}]},{"docId":"A_0021","docUri":"A_0021.html","score":1,"contexts":[{"form":"anlaßt","weight":"1","pos":1444,"context":"...Prof.essor Schrötter zu der Erklärung ver- <mark>anlaßt<\/mark>, daß er nicht die Mitglieder der Commission,...","fid":"p__19"}]},{"docId":"A_0029","docUri":"A_0029.html","score":1,"contexts":[{"form":"anlaßt","weight":"1","pos":358,"context":"...Rück- sicht auf Schicklichkeit habe ihn ver- <mark>anlaßt<\/mark> die Sitzungsberichte soviel als möglich auf das wissenschaft-...","fid":"p__24"}]},{"docId":"A_0074","docUri":"A_0074.html","score":1,"contexts":[{"form":"anlaßt","weight":"1","pos":197,"context":"...dieselbe unter den ange- gebenen Modalitaten ver- <mark>anlaßt<\/mark> werde. Die Auf- lage wird auf 500 Exem-...","fid":"p__12"}]},{"docId":"A_0023","docUri":"A_0023.html","score":1,"contexts":[{"form":"anlaßt","weight":"1","pos":491,"context":"...welche die Herren Mitglieder darüber zu machen ver- <mark>anlaßt<\/mark> werden sollten, nach Thunlich-","fid":"p__12"}]}]}