{"stem":"ausdrücken","instances":[{"docId":"C_0059","docUri":"C_0059.html","score":1,"contexts":[{"form":"ausdrücken","weight":"1","pos":204,"context":"...dem HerrnHrn. Rossi den Dank der kaiserlichen Akademie <mark>ausdrücken<\/mark> zu lassen, die Münzen selbst aber dem kaiserlich...","fid":"p__19"}]},{"docId":"A_0059","docUri":"A_0059.html","score":1,"contexts":[{"form":"ausdrücken","weight":"1","pos":72,"context":"...ben ihres Herrn Secretärs schriftlich der Akademie ihr Bedauern <mark>ausdrücken<\/mark> lassen bei der fei- erlichen Sitzung nicht erschei...","fid":"p__51"}]}]}