{"stem":"beigegeben","instances":[{"docId":"C_0004","docUri":"C_0004.html","score":1,"contexts":[{"form":"beigegeben","weight":"1","pos":1369,"context":"...Kunde, das etwa den monatlichen akademischen Be- richten <mark>beigegeben<\/mark> werden könnte, jedoch auch zum Be- sten der in...","fid":"p__10"}]},{"docId":"A_0023","docUri":"A_0023.html","score":1,"contexts":[{"form":"beigegeben","weight":"1","pos":1330,"context":"...und den Druckschriften als Anhang mit be- sonderem Titel <mark>beigegeben<\/mark> werden, deren Druck gleichzeitig mit den Abhandlungen der Mitglieder...","fid":"p__37"}]}]}