{"stem":"briefpost","instances":[{"docId":"A_0006","docUri":"A_0006.html","score":1,"contexts":[{"form":"Briefpost","weight":"1","pos":90,"context":"...der Betrag ermittelt, welchen das Fahrgeld in dem <mark>Briefpost<\/mark>-Eilwagen oder in dem Eisenbahnwagen erster Classe von...","fid":"p__38"}]},{"docId":"A_0027","docUri":"A_0027.html","score":1,"contexts":[{"form":"Briefpost","weight":"1","pos":1030,"context":"...Bezug auf das inländische Poeto ausgedehnt, ferner die <mark>Briefpost<\/mark> zur Annahme von Druck- schriften unter Kreuzband im...","fid":"p__20"}]}]}