{"stem":"böhmisch","instances":[{"docId":"A_0048","docUri":"A_0048.html","score":1,"contexts":[{"form":"böhmische","weight":"1","pos":305,"context":" Es wird beschlossen das <mark>böhmische<\/mark> Museum mit den Sitzungsberichten, Denkschriften, Fontes,...","fid":"p__11"}]},{"docId":"A_0098","docUri":"A_0098.html","score":1,"contexts":[{"form":"böhmische","weight":"1","pos":95,"context":" Die königlichkönigl. <mark>böhmische<\/mark> Gesellschaft der Wissenschaft- ten gibt der Akademie bekannt,...","fid":"p__14"}]}]}