{"stem":"demonstrationen","instances":[{"docId":"A_0016","docUri":"A_0016.html","score":1,"contexts":[{"form":"Demonstrationen","weight":"1","pos":2341,"context":"...Inn- und Anslandes zu streng wissenschaftlichen Vorträge und <mark>Demonstrationen<\/mark> in den Localitäten der ihr unterstehenden Institute unter be-...","fid":"p__36"}]},{"docId":"A_0008","docUri":"A_0008.html","score":1,"contexts":[{"form":"Demonstrationen","weight":"1","pos":152,"context":"...mein- te die Akademie solle sich nicht mit politischen <mark>Demonstrationen<\/mark> befassen,","fid":"p__11"}]}]}