{"stem":"dererseit","instances":[{"docId":"C_0073","docUri":"C_0073.html","score":1,"contexts":[{"form":"dererseits","weight":"1","pos":818,"context":"...im Stande wären eine selbstständige Prüfung vorzunehmen; an- <mark>dererseits<\/mark> aber bei einer ausserordentlichen bloß dieser Formalität wegen stattfin...","fid":"p__39"}]},{"docId":"A_0046","docUri":"A_0046.html","score":1,"contexts":[{"form":"dererseits","weight":"1","pos":561,"context":"...- sehenen Veränderungen über- schreiten zu dürfen; da an- <mark>dererseits<\/mark> durch die zu erwar- tende allerhöchste Bestätigung der...","fid":"p__49"}]}]}