{"stem":"dvhammer-purgstal","instances":[{"docId":"C_0034","docUri":"C_0034.html","score":1,"contexts":[{"form":"DvHammer-Purgstall","weight":"1","pos":251,"context":" <mark>DvHammer-Purgstall<\/mark> FWolf","fid":"p__7"}]},{"docId":"A_0026","docUri":"A_0026.html","score":1,"contexts":[{"form":"DvHammer-Purgstall","weight":"1","pos":2949,"context":" <mark>DvHammer-Purgstall<\/mark>","fid":"p__4"}]},{"docId":"C_0046","docUri":"C_0046.html","score":1,"contexts":[{"form":"DvHammer-Purgstall","weight":"1","pos":313,"context":" <mark>DvHammer-Purgstall<\/mark>","fid":"p__3"}]},{"docId":"C_0047","docUri":"C_0047.html","score":1,"contexts":[{"form":"DvHammer-Purgstall","weight":"1","pos":160,"context":" <mark>DvHammer-Purgstall<\/mark>","fid":"p__7"}]},{"docId":"C_0036","docUri":"C_0036.html","score":1,"contexts":[{"form":"DvHammer-Purgstall","weight":"1","pos":430,"context":" <mark>DvHammer-Purgstall<\/mark> FerdWolf","fid":"p__8"}]},{"docId":"C_0037","docUri":"C_0037.html","score":1,"contexts":[{"form":"DvHammer-Purgstall","weight":"1","pos":306,"context":" <mark>DvHammer-Purgstall<\/mark> FerdWolf","fid":"p__6"}]},{"docId":"C_0048","docUri":"C_0048.html","score":1,"contexts":[{"form":"DvHammer-Purgstall","weight":"1","pos":143,"context":" <mark>DvHammer-Purgstall<\/mark>","fid":"p__8"}]},{"docId":"C_0035","docUri":"C_0035.html","score":1,"contexts":[{"form":"DvHammer-Purgstall","weight":"1","pos":243,"context":" <mark>DvHammer-Purgstall<\/mark> FWolf ","fid":"p__9"}]}]}