{"stem":"erwidert","instances":[{"docId":"C_0005","docUri":"C_0005.html","score":2,"contexts":[{"form":"erwidert","weight":"1","pos":280,"context":" Herr Regierungsrath Endli-cher <mark>erwidert<\/mark>, daß er dieses Recht, Berichte zu machen, welche...","fid":"p__14"},{"form":"erwidert","weight":"1","pos":359,"context":" Der Herr General-Secretär <mark>erwidert<\/mark>, es existiere allerdings ein Protokoll über die Präsidial...","fid":"p__12"}]},{"docId":"C_0007","docUri":"C_0007.html","score":1,"contexts":[{"form":"erwidert","weight":"1","pos":355,"context":" Herr Regierungsrath Endlicher <mark>erwidert<\/mark>; das seye kein bloßes Vor- wort, sondern...","fid":"p__12"}]},{"docId":"A_0026","docUri":"A_0026.html","score":1,"contexts":[{"form":"erwidert","weight":"1","pos":2575,"context":" (Der Präsident <mark>erwidert<\/mark> hierauf: Die Akademie sey ist eben das Organ...","fid":"p__10"}]},{"docId":"A_0021","docUri":"A_0021.html","score":1,"contexts":[{"form":"erwidert","weight":"1","pos":664,"context":"...dem Voranschlage nicht augenblicklich her- zustellen seyen, wurde <mark>erwidert<\/mark>, daß hier die Angabe runder Zahlen für die...","fid":"p__26"}]},{"docId":"A_0020","docUri":"A_0020.html","score":1,"contexts":[{"form":"erwidert","weight":"1","pos":1310,"context":" Der Herr Präsident <mark>erwidert<\/mark>, daß ja, wenn eine Vergütung der übernommenen Vorträge...","fid":"p__13"}]},{"docId":"A_0009","docUri":"A_0009.html","score":1,"contexts":[{"form":"erwidert","weight":"1","pos":1327,"context":" Der General-Secretär <mark>erwidert<\/mark>, daß gewiß keines der anwesenden Mitglieder von dem...","fid":"p__22"}]},{"docId":"A_0006","docUri":"A_0006.html","score":1,"contexts":[{"form":"erwidert","weight":"1","pos":705,"context":" Der General-Secretär <mark>erwidert<\/mark>, daß er dann dieses Schreiben dem Herrn Vice...","fid":"p__14"}]},{"docId":"C_0063","docUri":"C_0063.html","score":1,"contexts":[{"form":"erwidert","weight":"1","pos":343,"context":" Grillparzer <mark>erwidert<\/mark> hierauf, er für seinen Theil nehme keinen Anstand...","fid":"p__29"}]},{"docId":"C_0006","docUri":"C_0006.html","score":1,"contexts":[{"form":"erwidert","weight":"1","pos":400,"context":"...der deutschen Hauptsprachen und Mundarten. Herr Regierungsrath Endlicher <mark>erwidert<\/mark>, er könne in der Wissenschaft keine Be- vorzugung...","fid":"p__23"}]},{"docId":"A_0013","docUri":"A_0013.html","score":1,"contexts":[{"form":"erwidert","weight":"1","pos":711,"context":" Professor Schrötter <mark>erwidert<\/mark>, es sey keineswegs die Absicht der Commission die...","fid":"p__28"}]},{"docId":"A_0019","docUri":"A_0019.html","score":1,"contexts":[{"form":"erwidert","weight":"1","pos":725,"context":" Der General-Secretär <mark>erwidert<\/mark>, daß der von ihm gestellte Antrag mit der...","fid":"p__23"}]},{"docId":"A_0029","docUri":"A_0029.html","score":1,"contexts":[{"form":"erwidert","weight":"1","pos":459,"context":" Der Secretär <mark>erwidert<\/mark> es könne sich hier nur um den letzten Vortrag...","fid":"p__14"}]},{"docId":"A_0023","docUri":"A_0023.html","score":1,"contexts":[{"form":"erwidert","weight":"1","pos":617,"context":"...- fassung mitgetheilt werden sollen. Der General-Secretär <mark>erwidert<\/mark>, der Gegenstand sey in der letzten Sitzung der...","fid":"p__27"}]}]}