{"stem":"freiexemplar","instances":[{"docId":"C_0031","docUri":"C_0031.html","score":1,"contexts":[{"form":"Freiexemplare","weight":"1","pos":210,"context":"...und Honorar 800 Guldenfl.Gulden. und 50 <mark>Freiexemplare<\/mark> zu er- wirken, gegen dem, daß das","fid":"p__16"}]},{"docId":"A_0093","docUri":"A_0093.html","score":1,"contexts":[{"form":"Freiexemplare","weight":"1","pos":97,"context":" 2o Sie bewilliget dem Ver- fasser 25 <mark>Freiexemplare<\/mark>, und schreibt ihm diese, so- wie die, welche...","fid":"p__19"}]},{"docId":"C_0100","docUri":"C_0100.html","score":1,"contexts":[{"form":"Freiexemplare","weight":"1","pos":293,"context":"...– für alles übrige à 16 Guldenfr und 50 <mark>Freiexemplare<\/mark> ihm zu bewilligen; gegen dem, daß das Werk...","fid":"p__45"}]}]}