{"stem":"geführten","instances":[{"docId":"A_0009","docUri":"A_0009.html","score":1,"contexts":[{"form":"geführten","weight":"1","pos":215,"context":"...zu schmücken, welche die nach Antiken getreu aus- <mark>geführten<\/mark> Bildnisse der Heroen der Wissenschaft aus der Griechen-...","fid":"p__31"}]},{"docId":"A_0023","docUri":"A_0023.html","score":1,"contexts":[{"form":"geführten","weight":"1","pos":437,"context":"...haidinger wünscht, daß die vom General-Secretär <mark>geführten<\/mark> Bücher derart jedem Mitgliede zur Einsicht offen stehen mögen,...","fid":"p__15"}]}]}