{"stem":"gegnet","instances":[{"docId":"C_0006","docUri":"C_0006.html","score":1,"contexts":[{"form":"gegnet","weight":"1","pos":891,"context":" Herr Regierungsrath Endlicher ent- <mark>gegnet<\/mark>: Andere Akademien seyen gleich bei ihrer Gründung durch...","fid":"p__8"}]},{"docId":"A_0030","docUri":"A_0030.html","score":1,"contexts":[{"form":"gegnet","weight":"1","pos":1192,"context":" Freiherr v. Münch ent- <mark>gegnet<\/mark>, daß er hier nicht als Mitglied der Classe...","fid":"p__11"}]},{"docId":"A_0019","docUri":"A_0019.html","score":1,"contexts":[{"form":"gegnet","weight":"1","pos":611,"context":" Der Herr Vice-Präsident ent- <mark>gegnet<\/mark>, daß die Lehrfreiheit nur dar- auf sich...","fid":"p__11"}]},{"docId":"A_0029","docUri":"A_0029.html","score":1,"contexts":[{"form":"gegnet","weight":"1","pos":685,"context":" Der Herr Vice-Präsident ent- <mark>gegnet<\/mark>, daß eine Zuschrift an den General-Secretär...","fid":"p__10"}]}]}