{"stem":"gräflich","instances":[{"docId":"C_0055","docUri":"C_0055.html","score":2,"contexts":[{"form":"gräflich","weight":"1","pos":418,"context":"...HerrHerr. Arneth einen an ihn gerichteten Brief des <mark>gräflich<\/mark> Herberstein'schen Beamten HerrnHrn. Koschuell in Gratz mit, worin...","fid":"p__27"},{"form":"gräflich","weight":"1","pos":435,"context":"...des berühmten Reisenden Sigmund vonv. HerbersteinHerberste und des <mark>gräflich<\/mark> Herberstein'schen Urkunden-Verzeichnisses einzu- senden.","fid":"p__27"}]}]}