{"stem":"haleb","instances":[{"docId":"C_0070","docUri":"C_0070.html","score":2,"contexts":[{"form":"Haleb","weight":"1","pos":189,"context":"...meine wissenschaftliche Thätig- keit während des Aufenthaltes in <mark>Haleb<\/mark>;\" 2. Auszüge aus Ibn-osch-Schihne's...","fid":"p__32"},{"form":"Haleb","weight":"1","pos":196,"context":"...Auszüge aus Ibn-osch-Schihne's Geschichte von <mark>Haleb<\/mark>;\" mit dem Antrage beide in dem Sitzungsbericht vom...","fid":"p__32"}]},{"docId":"C_0072","docUri":"C_0072.html","score":1,"contexts":[{"form":"Haleb","weight":"1","pos":190,"context":"...Kremer einge- sandten Aufsätze: \"Die Medreseen von <mark>Haleb<\/mark> und mekka\" zum Abdruck in dem heutigen Sitzungsbericht...","fid":"p__29"}]},{"docId":"C_0071","docUri":"C_0071.html","score":1,"contexts":[{"form":"Haleb","weight":"1","pos":234,"context":"...Die Medreseen in damaskus; 2). Die Medreseen in <mark>Haleb<\/mark> und mekka.","fid":"p__13"}]}]}