{"stem":"hervorgeht","instances":[{"docId":"A_0096","docUri":"A_0096.html","score":1,"contexts":[{"form":"hervorgeht","weight":"1","pos":692,"context":"...- sten Prüfung unterzieht, was am besten daraus <mark>hervorgeht<\/mark>, daß alle Com-","fid":"p__10"}]},{"docId":"A_0076","docUri":"A_0076.html","score":1,"contexts":[{"form":"hervorgeht","weight":"1","pos":133,"context":"...Secretär gibt die näheren hierauf bezüglichen Erläuterungen aus welchen <mark>hervorgeht<\/mark>, daß die Akademie ganz","fid":"p__13"}]}]}