{"stem":"landmarschal","instances":[{"docId":"A_0004","docUri":"A_0004.html","score":2,"contexts":[{"form":"Landmarschall","weight":"1","pos":908,"context":" <mark>Landmarschall<\/mark> Grafen von Montecuccoli vom 12. Jänner auf das Ansuchen...","fid":"p__10"},{"form":"Landmarschall","weight":"1","pos":926,"context":" Die Akademie beschließt, daß dem Herrn <mark>Landmarschall<\/mark> und den ständischen Verordneten seiner Zeit für die be-...","fid":"p__9"}]},{"docId":"A_0067","docUri":"A_0067.html","score":1,"contexts":[{"form":"Landmarschall","weight":"1","pos":134,"context":" SeineSne Excellenz der Herr <mark>Landmarschall<\/mark> eröffnet in einer Note vom 14. April dieses Jahresd...","fid":"p__20"}]},{"docId":"A_0089","docUri":"A_0089.html","score":1,"contexts":[{"form":"Landmarschalls","weight":"1","pos":74,"context":" Schreiben SeinerSer Excellenz des Herrn <mark>Landmarschalls<\/mark> Franz Grafen von Beroldingen vom 4. April dieses Jahresd...","fid":"p__26"}]},{"docId":"A_0110","docUri":"A_0110.html","score":1,"contexts":[{"form":"Landmarschalls","weight":"1","pos":122,"context":" Note SeinerSer Excellenz des Herrn <mark>Landmarschalls<\/mark>, Gra- fen von Beroldingens","fid":"p__12"}]}]}