{"stem":"lass","instances":[{"docId":"A_0022","docUri":"A_0022.html","score":3,"contexts":[{"form":"lasse","weight":"1","pos":1209,"context":"...noch eine Zeit lang zuzuwarten. Uibri- gens <mark>lasse<\/mark> sich in dieser Sache ohne ir- gend Jemanden zu...","fid":"p__29"},{"form":"lasse","weight":"1","pos":1280,"context":"...sich auf eine zarte Weise in einem Schreiben anbringen <mark>lasse<\/mark>, worin er den Herrn Baron um die Mittheilung...","fid":"p__13"},{"form":"lasse","weight":"1","pos":1727,"context":"...lich sey, ob sich ein solcher Ausschuß bilden <mark>lasse<\/mark>. An geeignetsten wä- re die Commission diesen Aus-...","fid":"p__9"}]},{"docId":"C_0006","docUri":"C_0006.html","score":2,"contexts":[{"form":"lasse","weight":"1","pos":500,"context":"...stelle die Resultate der früheren in Zweifel, besonders <mark>lasse<\/mark> sie in Hinsicht der Mund- arten noch viel...","fid":"p__25"},{"form":"lasse","weight":"1","pos":1036,"context":"...er sich außerhalb seines Libe- ralismus wegen preisen <mark>lasse<\/mark>.","fid":"p__16"}]},{"docId":"A_0149","docUri":"A_0149.html","score":1,"contexts":[{"form":"lasse","weight":"1","pos":145,"context":"...oifizwa i der itzteg dev phlah- höste wischer <mark>lasse<\/mark> vom 2Merz rrich ertellet ha","fid":"p__9"}]},{"docId":"A_0048","docUri":"A_0048.html","score":1,"contexts":[{"form":"lasses","weight":"1","pos":365,"context":"...des von Herrn Taitbout de Ma- rigny herausgegebenen At- <mark>lasses<\/mark> zu einer Hydrogra- phie de la mer noire...","fid":"p__14"}]},{"docId":"A_0007","docUri":"A_0007.html","score":1,"contexts":[{"form":"lasse","weight":"1","pos":529,"context":"...Empfänge aus der Casse Rechnung zu legen. Es <mark>lasse<\/mark> sich dieses auf zwei Arten bewerk- stelligen....","fid":"p__37"}]},{"docId":"C_0068","docUri":"C_0068.html","score":1,"contexts":[{"form":"lasse","weight":"1","pos":493,"context":"...der Be- theiligung der Classe werthes Resultat sich erwarten <mark>lasse<\/mark>, wenn dieser nämlich sich auch","fid":"p__16"}]},{"docId":"A_0026","docUri":"A_0026.html","score":1,"contexts":[{"form":"lasse","weight":"1","pos":2556,"context":" Der General-Secretär äu- ßert: Es <mark>lasse<\/mark> sich wohl nichts dagegen einwenden, daß die Akademie...","fid":"p__16"}]},{"docId":"A_0021","docUri":"A_0021.html","score":1,"contexts":[{"form":"lasse","weight":"1","pos":180,"context":"...sowohl der Hof- bibliothek als unserer Akademie zukommen <mark>lasse<\/mark>.","fid":"p__4"}]},{"docId":"A_0009","docUri":"A_0009.html","score":1,"contexts":[{"form":"lasse","weight":"1","pos":925,"context":"...Präsident, daß dieselbe sich jetzt noch nicht beantworten <mark>lasse<\/mark>; man müsse sich vorher mit den Competenten in...","fid":"p__19"}]},{"docId":"C_0057","docUri":"C_0057.html","score":1,"contexts":[{"form":"lasse","weight":"1","pos":159,"context":"...Classe beschließt HerrnHrn. Pichler auffordern zu lassen,<mark>lasse<\/mark> die Abhandlung der Akademie einzusenden, um ihrer Ge-...","fid":"p__17"}]},{"docId":"C_0085","docUri":"C_0085.html","score":1,"contexts":[{"form":"lasse","weight":"1","pos":296,"context":"...Papieren des Verstorbenen vorfinden oder aus seinen Vorarbeiten herstellen <mark>lasse<\/mark>, und wenn sich ein Conven- tuale seines...","fid":"p__41"}]},{"docId":"C_0067","docUri":"C_0067.html","score":1,"contexts":[{"form":"lasse","weight":"1","pos":441,"context":"...Ver gütung selbst der höheren Kosten sich entgegen sehen <mark>lasse<\/mark>. Um daher dem Verfasser einen Beweis einen Beweis...","fid":"p__16"}]},{"docId":"C_0016","docUri":"C_0016.html","score":1,"contexts":[{"form":"lasse","weight":"1","pos":119,"context":"...Bericht über die Grammatica aegyptiaca aus Wenrich's handschriftlichem Nach- <mark>lasse<\/mark>, und zeigt, daß sie nur ein Aus-...","fid":"p__18"}]},{"docId":"A_0013","docUri":"A_0013.html","score":1,"contexts":[{"form":"lasse","weight":"1","pos":928,"context":"...abgeschlossen werden, was man dem Secretär zu thun über- <mark>lasse<\/mark>.","fid":"p__15"}]},{"docId":"A_0029","docUri":"A_0029.html","score":1,"contexts":[{"form":"lasse","weight":"1","pos":1247,"context":"...es sich im Allgemei- nen wohl nicht entscheiden <mark>lasse<\/mark> ob die Akademie auf schieds- richterliche Urtheile einzugehen...","fid":"p__11"}]},{"docId":"A_0034","docUri":"A_0034.html","score":1,"contexts":[{"form":"lasse","weight":"1","pos":486,"context":"...500 fl.Gulden füglich auf 300 fl.Gulden herabsetzen <mark>lasse<\/mark>, so daß immer- hin die Remunerirung des Rechungsführers...","fid":"p__27"}]}]}