{"stem":"ment","instances":[{"docId":"C_0092","docUri":"C_0092.html","score":1,"contexts":[{"form":"mente\"","weight":"1","pos":641,"context":"..., über die Frage: ob die \"Frag- <mark>mente\"<\/mark> in den Sitzungsberich- ten abzudrucken seien, oder deren...","fid":"p__29"}]},{"docId":"C_0006","docUri":"C_0006.html","score":1,"contexts":[{"form":"mentes","weight":"1","pos":407,"context":"...vorzugung, und sey es des deutschen Ele- <mark>mentes<\/mark>, anerkennen; wenn andere Sprachen einer wissenschaftlichen Bear...","fid":"p__23"}]},{"docId":"A_0008","docUri":"A_0008.html","score":1,"contexts":[{"form":"ment","weight":"1","pos":332,"context":"...nur Verberathungen zu ei- nem künftigen deutschen Parla- <mark>ment<\/mark> im Sinne.","fid":"p__30"}]}]}