{"stem":"moth","instances":[{"docId":"A_0012","docUri":"A_0012.html","score":2,"contexts":[{"form":"Moth","weight":"1","pos":476,"context":"...Gintl 19 Stimmen\" Löwe 18 Stimmen\" Hruschauer 17 Stimmen\" <mark>Moth<\/mark> 17 Stimmen\" Balling 16 Stimmen\" reissek 16 Stimmen\" Reichenbach...","fid":"p__121"},{"form":"Moth","weight":"1","pos":568,"context":" Balling Freyer Fuchs Gintl Hruschauer Löwe <mark>Moth<\/mark> Reichenbach reissek Rochleder Salomon Wertheim TheodorTheod. Wertheim WilhelmWilh...","fid":"p__33"}]}]}