{"stem":"pedantischem","instances":[{"docId":"A_0016","docUri":"A_0016.html","score":2,"contexts":[{"form":"pedantischem","weight":"1","pos":1986,"context":"...Zu einem solchen Beschluße müssen wir uns ohne vielem <mark>pedantischem<\/mark> Grübeln einigen und denselben früher noch in's Werk setzen...","fid":"p__17"},{"form":"pedantischem","weight":"1","pos":2127,"context":"...Zu einem solchen Beschluße müssen wir uns ohne vielem <mark>pedantischem<\/mark> Grübeln einigen und denselben früher noch in's Werk setzen...","fid":"p__17"}]}]}