{"stem":"recht","instances":[{"docId":"A_0073","docUri":"A_0073.html","score":1,"contexts":[{"form":"Rechts","weight":"1","pos":195,"context":"...- sophisch-historischen Classe auch die k. k. <mark>Rechts<\/mark>-Akade- mien zu","fid":"p__25"}]},{"docId":"C_0052","docUri":"C_0052.html","score":1,"contexts":[{"form":"rechts\"","weight":"1","pos":58,"context":" seines \"Mosaischrabbinischen Civil- <mark>rechts\"<\/mark> im Manuscript, mit dem Ge- suche um Prüfung...","fid":"p__19"}]},{"docId":"C_0004","docUri":"C_0004.html","score":1,"contexts":[{"form":"Rechts","weight":"1","pos":794,"context":"...Franz Roessler, außerordentlichem Professor \/:Docenten:\/ der <mark>Rechts<\/mark>-Geschichte an der kaiserlich-königlichenk. k....","fid":"p__17"}]},{"docId":"A_0074","docUri":"A_0074.html","score":1,"contexts":[{"form":"rechts","weight":"1","pos":211,"context":" 9. December dieses Jahresd.J. über An- Scan <mark>rechts<\/mark> abgeschnitten hören des betreffenden Commissions-Berichtes be- schlossen...","fid":"p__44"}]}]}