{"stem":"san","instances":[{"docId":"C_0085","docUri":"C_0085.html","score":2,"contexts":[{"form":"San","weight":"1","pos":79,"context":"...er die Classe ersucht, sich bei der Bibliothek <mark>San<\/mark> Marco in Ve-nedig zu verwenden, damit dem...","fid":"p__30"},{"form":"San","weight":"1","pos":125,"context":"..., an die Direction der Bib- liothek von <mark>San<\/mark> Marco im Namen der Classe zu schreiben und um...","fid":"p__11"}]},{"docId":"C_0081","docUri":"C_0081.html","score":1,"contexts":[{"form":"SanS","weight":"1","pos":219,"context":"...königlichenkk. Hofbiblio- thek oder aus der von <mark>SanS<\/mark>. Marco.","fid":"p__13"}]},{"docId":"C_0082","docUri":"C_0082.html","score":1,"contexts":[{"form":"SanS","weight":"1","pos":189,"context":"...der Classe beschlossen, nicht nur die Bibliothek von <mark>SanS<\/mark>. Marco sondern alle 26 Bibliotheken der Monarchie,...","fid":"p__14"}]}]}