{"stem":"sol","instances":[{"docId":"A_0015","docUri":"A_0015.html","score":4,"contexts":[{"form":"sol","weight":"1","pos":623,"context":"...Unterstützungen im Gelde beziehe, denn es hätten in <mark>sol<\/mark>- chem Falle die in den Provinzen be- findlichen...","fid":"p__28"},{"form":"sol","weight":"1","pos":700,"context":".... Die Ausschlie- ßung von der Akademie wurde <mark>sol<\/mark>- che Männer der Wissenschaft entziehen, wenn nicht...","fid":"p__36"},{"form":"sol","weight":"1","pos":1094,"context":"...diese Thätigkeit kann sie unterstützen, sie kann die <mark>sol<\/mark>- cher Weise entstehenden Arbeiten in ihre Schriften aufnehmen...","fid":"p__15"},{"form":"sol","weight":"1","pos":1139,"context":"...Zwecke ins Leben zu rufen; aber diese Vereine <mark>sol<\/mark>- len sich authonomisch bewegen; Die Akademie soll...","fid":"p__23"}]},{"docId":"A_0007","docUri":"A_0007.html","score":2,"contexts":[{"form":"sol","weight":"1","pos":1335,"context":"...findet keinen An- stand daß dieses geschehe, denn <mark>sol<\/mark>- che Mitglieder können nur bei wissen- schaftlichen Verhandlungen...","fid":"p__14"},{"form":"sol","weight":"1","pos":1343,"context":"...schaftlichen Verhandlungen zugegen seyn. Bei Abstimmungen, wenn <mark>sol<\/mark>- che in Gegenwart nicht wirklicher Mitglieder vorkommen,...","fid":"p__14"}]},{"docId":"A_0026","docUri":"A_0026.html","score":2,"contexts":[{"form":"sol","weight":"1","pos":407,"context":"...als europäischer Bedeu- lung entschließen. Als ein <mark>sol<\/mark>- ches erscheine ihm die Herausgabe der Acta Conciliorum...","fid":"p__17"},{"form":"sol","weight":"1","pos":706,"context":"...dieses Unternehmen sich einlassen wolle, ihm zu einer <mark>sol<\/mark>- chen Reise sogleich einen chen Urlaub von dem...","fid":"p__16"}]},{"docId":"A_0016","docUri":"A_0016.html","score":1,"contexts":[{"form":"sol","weight":"1","pos":946,"context":"...den Unter- richt bestimmten Sammlungen der Akademie untergeordnet werden <mark>sol<\/mark>- len, da ja alle Samlungen wenig- stens...","fid":"p__13"}]},{"docId":"A_0022","docUri":"A_0022.html","score":1,"contexts":[{"form":"sol","weight":"1","pos":1060,"context":"...ja nicht einmal auf die Einladungsschreiben geantwortet, als <mark>sol<\/mark>- che betrachten zu dürfen, welche still- schweigend...","fid":"p__8"}]},{"docId":"A_0020","docUri":"A_0020.html","score":1,"contexts":[{"form":"sol","weight":"1","pos":1408,"context":"...geworden seyn, wenn es annehmen wollte, daß ein <mark>sol<\/mark>- cher Professor keine weitern Einkünf- te als...","fid":"p__34"}]},{"docId":"A_0096","docUri":"A_0096.html","score":1,"contexts":[{"form":"sol","weight":"1","pos":639,"context":"...zu dür- fen, zumal, wenn nur <mark>sol<\/mark>- che Abänderung keine nur einigermaßen tief greifen-...","fid":"p__7"}]},{"docId":"A_0076","docUri":"A_0076.html","score":1,"contexts":[{"form":"sol","weight":"1","pos":334,"context":" Die Akademie ermächtiget den Generalsecretär einen <mark>sol<\/mark>- chen Aushelfer gegen den bean- tragten Lohn...","fid":"p__9"}]},{"docId":"A_0030","docUri":"A_0030.html","score":1,"contexts":[{"form":"sol","weight":"1","pos":207,"context":"...wenn auch nach einem be- schränkteren Plane. Ein <mark>sol<\/mark>- cher würde keine Früchte brin- gen....","fid":"p__27"}]},{"docId":"C_0075","docUri":"C_0075.html","score":1,"contexts":[{"form":"sol","weight":"1","pos":489,"context":"...sei, andere ausländische Mitarbeiter dann mit demselben Rechte eine <mark>sol<\/mark>- che Vergütung beanspruchen könnten, was der Akademie...","fid":"p__29"}]},{"docId":"A_0029","docUri":"A_0029.html","score":1,"contexts":[{"form":"sol","weight":"1","pos":1370,"context":"...Fall zu Fall gegeben oder un- bedingt abgelehnt werden <mark>sol<\/mark>- len erklären sich die Herren: Brücke,...","fid":"p__17"}]},{"docId":"C_0107","docUri":"C_0107.html","score":1,"contexts":[{"form":"sol","weight":"1","pos":383,"context":"...reitwilligkeit der Classe er- klären zu lassen, eine <mark>sol<\/mark>- che Unterstützung von der Gesammt-Akademie erwir...","fid":"p__36"}]},{"docId":"A_0034","docUri":"A_0034.html","score":1,"contexts":[{"form":"sol","weight":"1","pos":791,"context":"...21 Stimmen ge- gen 4 entschieden, daß eine <mark>sol<\/mark>- che Anfrage nicht Statt finden solle.","fid":"p__13"}]},{"docId":"A_0049","docUri":"A_0049.html","score":1,"contexts":[{"form":"sol","weight":"1","pos":145,"context":"...ge- setzt und die dazu nöthigen Schritte gemacht werden <mark>sol<\/mark>- len, was genehmigt wird.","fid":"p__6"}]},{"docId":"A_0014","docUri":"A_0014.html","score":1,"contexts":[{"form":"sol","weight":"1","pos":453,"context":" veranschlagte Gewehr, wenn <mark>sol<\/mark>- ches vom Nationalgarde-Depot ge- faßt wird,...","fid":"p__28"}]},{"docId":"A_0023","docUri":"A_0023.html","score":1,"contexts":[{"form":"sol","weight":"1","pos":1406,"context":"...Inhaltes an die Bibliothek des polytechnischen Instituts abgegeben werden <mark>sol<\/mark>- len?","fid":"p__15"}]},{"docId":"C_0003","docUri":"C_0003.html","score":1,"contexts":[{"form":"sol","weight":"1","pos":359,"context":"...machen, wie es schicklich wäre, wenn die Akademie bei <mark>sol<\/mark>- chen Trauerfeierlichkeiten zu Ehren eines ihrer Mitglieder sich...","fid":"p__15"}]},{"docId":"A_0011","docUri":"A_0011.html","score":1,"contexts":[{"form":"sol","weight":"1","pos":611,"context":" gegen die Nothwendigkeit einer <mark>sol<\/mark>- chen Commission. Die HerrnHrn. Burg,...","fid":"p__31"}]}]}