{"stem":"stall","instances":[{"docId":"C_0062","docUri":"C_0062.html","score":1,"contexts":[{"form":"stall","weight":"1","pos":219,"context":" Freiherr Hammer-Purg-<mark>stall<\/mark> liest die Fortsetzung seiner Abhandlung über die Namen der...","fid":"p__8"}]},{"docId":"C_0063","docUri":"C_0063.html","score":1,"contexts":[{"form":"stall","weight":"1","pos":359,"context":"...Arbeiten finde. f. Freiherr Hammer-Purg-<mark>stall<\/mark> bringt ferner die Frage in Anregung, ob nicht...","fid":"p__29"}]},{"docId":"A_0107","docUri":"A_0107.html","score":1,"contexts":[{"form":"stall","weight":"1","pos":127,"context":"...das verstorbene Mitglied Freiherr von Hammer-Purg-<mark>stall<\/mark> der kaiserlichenkais. Akade- mie ein Legat vermacht...","fid":"p__19"}]}]}