{"stem":"umso","instances":[{"docId":"A_0035","docUri":"A_0035.html","score":1,"contexts":[{"form":"umso","weight":"1","pos":446,"context":"...Bitte die Akademie wolle für die nöthig werdende Substitution <mark>umso<\/mark>- mehr Vorsorge treffen, als sein Herrn College...","fid":"p__26"}]},{"docId":"A_0030","docUri":"A_0030.html","score":1,"contexts":[{"form":"umso","weight":"1","pos":655,"context":"...nothwendig es sei eine wissenschaftliche Zeit- schrift zu haben, <mark>umso<\/mark>- mehr jetzt, da die wiener","fid":"p__38"}]}]}