{"stem":"voranschläg","instances":[{"docId":"A_0006","docUri":"A_0006.html","score":2,"contexts":[{"form":"Voranschläge","weight":"1","pos":812,"context":" IV. Der General-Secretär legt die <mark>Voranschläge<\/mark> der Ausgaben für das Verwaltungsjahr 1848 vor. Er bemerkt...","fid":"p__12"},{"form":"Voranschläge","weight":"1","pos":1098,"context":" Die obigen <mark>Voranschläge<\/mark> wurden sämmt- lich von der Akademie einstimmig an-...","fid":"p__5"}]},{"docId":"A_0022","docUri":"A_0022.html","score":1,"contexts":[{"form":"Voranschläge","weight":"1","pos":361,"context":"...sei. Der Secretär liest die für beide Classen entworfenen <mark>Voranschläge<\/mark>, welche zur Kenntniß genommen werden.","fid":"p__15"}]}]}