{"stem":"vorhergehend","instances":[{"docId":"A_0007","docUri":"A_0007.html","score":1,"contexts":[{"form":"vorhergehende","weight":"1","pos":890,"context":"...Jahre, sondern aus dem Reste der Dotation für das <mark>vorhergehende<\/mark> bestritten werden solle, wohin selbe eigentlich gehören....","fid":"p__9"}]},{"docId":"C_0055","docUri":"C_0055.html","score":1,"contexts":[{"form":"vorhergehende","weight":"1","pos":49,"context":" Das <mark>vorhergehende<\/mark> Sitzungs- protokoll ohne Änderung ange- nommen....","fid":"p__13"}]},{"docId":"A_0130","docUri":"A_0130.html","score":1,"contexts":[{"form":"vorhergehender","weight":"1","pos":123,"context":" <mark>vorhergehender<\/mark> Anfrage unter den früheren Modali- täten zu verwenden...","fid":"p__4"}]}]}