{"stem":"vortheilhaftest","instances":[{"docId":"A_0022","docUri":"A_0022.html","score":1,"contexts":[{"form":"vortheilhafteste","weight":"1","pos":1975,"context":"...in Anspruch nimmt; er werde hiebei auf die <mark>vortheilhafteste<\/mark> Weise zu Werken zu gehen trachten.","fid":"p__23"}]},{"docId":"A_0009","docUri":"A_0009.html","score":1,"contexts":[{"form":"vortheilhafteste","weight":"1","pos":939,"context":"...sie sich hierüber erklärt haben, kann die Akademie die <mark>vortheilhafteste<\/mark> Wahl treffen.","fid":"p__19"}]}]}