{"stem":"wahrlich","instances":[{"docId":"A_0016","docUri":"A_0016.html","score":2,"contexts":[{"form":"wahrlich","weight":"1","pos":1848,"context":"...und zugleich so fühlbar gewordene Thatsachen, daß es <mark>wahrlich<\/mark> nicht erst jener welterschütternden politischen Catastraphe bedurfte, um...","fid":"p__36"},{"form":"wahrlich","weight":"1","pos":2406,"context":"...Kräften dieses Ziel anzustreben, dann darf sie sich <mark>wahrlich<\/mark> nicht beklagen, wenn sie von der geistlosen Menge...","fid":"p__11"}]},{"docId":"A_0096","docUri":"A_0096.html","score":1,"contexts":[{"form":"wahrlich","weight":"1","pos":624,"context":" Es wäre <mark>wahrlich<\/mark> sehr traurig, wenn es der Aka- demie...","fid":"p__11"}]}]}